sorzun/__init__.py
sorzun/__main__.py
sorzun/cashaddr.py
sorzun/cashaddrconv.py
sorzun/deterministic.py
sorzun/ecc.py
sorzun/mnemonic.py
sorzun/util.py
sorzun/wordlists/english.txt
sorzun/wordlists/french.txt
sorzun/wordlists/italian.txt
sorzun/wordlists/japanese.txt
sorzun/wordlists/korean.txt
sorzun/wordlists/spanish.txt
sorzun-0.1.0.dist-info/METADATA
sorzun-0.1.0.dist-info/WHEEL
sorzun-0.1.0.dist-info/entry_points.txt
sorzun-0.1.0.dist-info/top_level.txt
sorzun-0.1.0.dist-info/RECORD
